inline_sql/__about__.py
inline_sql/__init__.py
inline_sql/_src/executor.py
inline_sql/_src/runtime.py
inline_sql-0.1.2.dist-info/METADATA
inline_sql-0.1.2.dist-info/WHEEL
inline_sql-0.1.2.dist-info/licenses/LICENSE
inline_sql-0.1.2.dist-info/RECORD
