Metadata-Version: 2.1
Name: inline-sql
Version: 0.1.2
Summary: Inline SQL in any Python program, on local dataframes
Project-URL: Documentation, https://github.com/ekzhang/inline-sql#readme
Project-URL: Issues, https://github.com/ekzhang/inline-sql/issues
Project-URL: Source, https://github.com/ekzhang/inline-sql
Author-email: Eric Zhang <ekzhang1@gmail.com>
License-Expression: MIT
License-File: LICENSE
Keywords: database,language,sql
Classifier: Development Status :: 4 - Beta
Classifier: Intended Audience :: Developers
Classifier: License :: OSI Approved :: MIT License
Classifier: Programming Language :: Python :: 3.7
Classifier: Programming Language :: Python :: 3.8
Classifier: Programming Language :: Python :: 3.9
Classifier: Programming Language :: Python :: 3.10
Classifier: Programming Language :: SQL
Classifier: Topic :: Database
Classifier: Topic :: Software Development :: Libraries
Requires-Python: >=3.7
Requires-Dist: duckdb>=0.5
Requires-Dist: pandas>=1.3
Requires-Dist: sqlparse>=0.4
